gokulsmodule/__init__.py
gokulsmodule/main.py
gokulsmodule-0.1.3.dist-info/licenses/LICENSE
gokulsmodule-0.1.3.dist-info/METADATA
gokulsmodule-0.1.3.dist-info/WHEEL
gokulsmodule-0.1.3.dist-info/top_level.txt
gokulsmodule-0.1.3.dist-info/RECORD
