Metadata-Version: 2.4
Name: gokulsmodule
Version: 0.1.3
Summary: Module has a lot of cool stuff in it :DDD
Home-page: https://github.com/TheGlork/GokulsModule
Author: NT Gokul
Author-email: gokulnt2008@gmail.com
Classifier: Programming Language :: Python :: 3
Classifier: License :: OSI Approved :: MIT License
Classifier: Operating System :: OS Independent
Requires-Python: >=3.6
License-File: LICENSE
Dynamic: author
Dynamic: author-email
Dynamic: classifier
Dynamic: description
Dynamic: description-content-type
Dynamic: home-page
Dynamic: license-file
Dynamic: requires-python
Dynamic: summary
